Radiko/__init__.py
Radiko/radiko.py
radiko-1.4.1.dist-info/LICENSE.txt
radiko-1.4.1.dist-info/METADATA
radiko-1.4.1.dist-info/WHEEL
radiko-1.4.1.dist-info/top_level.txt
radiko-1.4.1.dist-info/RECORD
