Metadata-Version: 2.1
Name: radiko
Version: 1.4.1
Summary: Radiko: Python製の非公式Radikoライブラリ
Home-page: https://github.com/kokarare1212/Radiko.py
Author: kokarare1212
Author-email: kokarare1212@gmail.com
License: Apache License 2.0
Platform: UNKNOWN
Classifier: Development Status :: 5 - Production/Stable
Classifier: Environment :: Console
Classifier: License :: OSI Approved :: Apache Software License
Classifier: Natural Language :: Japanese
Classifier: Programming Language :: Python :: 3.9
Classifier: Topic :: Multimedia :: Sound/Audio :: Players
Requires-Dist: defusedxml
Requires-Dist: requests
